dawdaw/utils.py
dawdaw/magic.py
dawdaw/states.py
dawdaw/__init__.py
dawdaw/modules.py
dawdaw-0.1.2.dist-info/metadata.json
dawdaw-0.1.2.dist-info/METADATA
dawdaw-0.1.2.dist-info/WHEEL
dawdaw-0.1.2.dist-info/RECORD
dawdaw-0.1.2.dist-info/top_level.txt
dawdaw-0.1.2.dist-info/DESCRIPTION.rst
