Metadata-Version: 2.0
Name: dawdaw
Version: 0.1.2
Summary: salt renderer for extremly lazy python dev
Home-page: https://github.com/Psycojoker/dawdaw
Author: Laurent Peuch
Author-email: cortex@worlddomination.be
License: beerware
Keywords: salt renderer
Platform: UNKNOWN
